{
  "annotations": {
    "list": [
      {
        "builtIn": 1,
        "datasource": "-- Grafana --",
        "enable": true,
        "hide": true,
        "iconColor": "rgba(0, 211, 255, 1)",
        "name": "Annotations & Alerts",
        "type": "dashboard"
      }
    ]
  },
  "editable": true,
  "gnetId": null,
  "graphTooltip": 0,
  "id": 1,
  "iteration": 1623338317060,
  "links": [],
  "panels": [
    {
      "datasource": null,
      "description": "Overall average response time",
      "fieldConfig": {
        "defaults": {
          "color": {
            "mode": "continuous-BlYlRd"
          },
          "custom": {},
          "decimals": 2,
          "mappings": [],
          "thresholds": {
            "mode": "percentage",
            "steps": [
              {
                "color": "green",
                "value": null
              },
              {
                "color": "green",
                "value": 300
              },
              {
                "color": "blue",
                "value": 500
              },
              {
                "color": "orange",
                "value": 1000
              },
              {
                "color": "red",
                "value": 3000
              }
            ]
          }
        },
        "overrides": []
      },
      "gridPos": {
        "h": 5,
        "w": 5,
        "x": 0,
        "y": 0
      },
      "id": 4,
      "options": {
        "orientation": "auto",
        "reduceOptions": {
          "calcs": [
            "mean"
          ],
          "fields": "",
          "values": false
        },
        "showThresholdLabels": false,
        "showThresholdMarkers": true
      },
      "pluginVersion": "7.3.7",
      "targets": [
        {
          "expr": "rate(endpoint_monitoring_sum{http_code=~\"2..\",endpoint_name=\"$endpoint\"}[30m])/rate(endpoint_monitoring_count{http_code=~\"2..\",endpoint_name=\"$endpoint\"}[30m])",
          "format": "time_series",
          "instant": false,
          "interval": "",
          "intervalFactor": 1,
          "legendFormat": "",
          "refId": "A"
        }
      ],
      "timeFrom": null,
      "timeShift": null,
      "title": "Response Average (ms)",
      "type": "gauge"
    },
    {
      "cards": {
        "cardPadding": null,
        "cardRound": null
      },
      "color": {
        "cardColor": "#b4ff00",
        "colorScale": "sqrt",
        "colorScheme": "interpolatePlasma",
        "exponent": 0.5,
        "min": 2,
        "mode": "spectrum"
      },
      "dataFormat": "tsbuckets",
      "datasource": null,
      "description": "Response duration (ms)",
      "fieldConfig": {
        "defaults": {
          "custom": {}
        },
        "overrides": []
      },
      "gridPos": {
        "h": 10,
        "w": 18,
        "x": 5,
        "y": 0
      },
      "heatmap": {},
      "hideZeroBuckets": false,
      "highlightCards": true,
      "id": 8,
      "legend": {
        "show": true
      },
      "pluginVersion": "7.3.7",
      "reverseYBuckets": false,
      "targets": [
        {
          "expr": "sum(increase(endpoint_monitoring_bucket{endpoint_name=\"$endpoint\"}[30m])) by (le)",
          "format": "heatmap",
          "instant": false,
          "interval": "",
          "intervalFactor": 1,
          "legendFormat": "{{le}} ms",
          "refId": "A"
        }
      ],
      "timeFrom": null,
      "timeShift": null,
      "title": "Response Duration",
      "tooltip": {
        "show": true,
        "showHistogram": false
      },
      "tooltipDecimals": null,
      "type": "heatmap",
      "xAxis": {
        "show": true
      },
      "xBucketNumber": null,
      "xBucketSize": "",
      "yAxis": {
        "decimals": null,
        "format": "short",
        "logBase": 1,
        "max": null,
        "min": null,
        "show": true,
        "splitFactor": null
      },
      "yBucketBound": "auto",
      "yBucketNumber": null,
      "yBucketSize": null
    },
    {
      "datasource": null,
      "fieldConfig": {
        "defaults": {
          "custom": {},
          "mappings": [],
          "thresholds": {
            "mode": "absolute",
            "steps": [
              {
                "color": "blue",
                "value": null
              },
              {
                "color": "green",
                "value": 80
              }
            ]
          }
        },
        "overrides": []
      },
      "gridPos": {
        "h": 5,
        "w": 5,
        "x": 0,
        "y": 5
      },
      "id": 10,
      "options": {
        "colorMode": "value",
        "graphMode": "area",
        "justifyMode": "auto",
        "orientation": "auto",
        "reduceOptions": {
          "calcs": [
            "mean"
          ],
          "fields": "",
          "values": false
        },
        "textMode": "auto"
      },
      "pluginVersion": "7.3.7",
      "targets": [
        {
          "expr": "sum(endpoint_monitoring_count{http_code=~\"2..\",endpoint_name=\"$endpoint\"})",
          "interval": "",
          "legendFormat": "",
          "refId": "A"
        }
      ],
      "timeFrom": null,
      "timeShift": null,
      "title": "HTTP 2XX Total",
      "type": "stat"
    },
    {
      "datasource": null,
      "description": "Number of HTTP 4XX responses - until now",
      "fieldConfig": {
        "defaults": {
          "custom": {},
          "mappings": [],
          "thresholds": {
            "mode": "absolute",
            "steps": [
              {
                "color": "green",
                "value": null
              },
              {
                "color": "red",
                "value": 80
              }
            ]
          }
        },
        "overrides": []
      },
      "gridPos": {
        "h": 5,
        "w": 5,
        "x": 0,
        "y": 10
      },
      "id": 12,
      "options": {
        "colorMode": "value",
        "graphMode": "area",
        "justifyMode": "auto",
        "orientation": "auto",
        "reduceOptions": {
          "calcs": [
            "mean"
          ],
          "fields": "",
          "values": false
        },
        "textMode": "auto"
      },
      "pluginVersion": "7.3.7",
      "targets": [
        {
          "expr": "sum(endpoint_monitoring_count{http_code=~\"4..\",endpoint_name=\"$endpoint\"})",
          "interval": "",
          "legendFormat": "",
          "refId": "A"
        }
      ],
      "timeFrom": null,
      "timeShift": null,
      "title": "HTTP 4XX Total",
      "type": "stat"
    },
    {
      "aliasColors": {},
      "bars": false,
      "dashLength": 10,
      "dashes": false,
      "datasource": null,
      "description": "HTTP Response Codes for the last 30 minutes",
      "fieldConfig": {
        "defaults": {
          "custom": {}
        },
        "overrides": []
      },
      "fill": 1,
      "fillGradient": 0,
      "gridPos": {
        "h": 10,
        "w": 18,
        "x": 5,
        "y": 10
      },
      "hiddenSeries": false,
      "id": 6,
      "legend": {
        "avg": false,
        "current": false,
        "max": false,
        "min": false,
        "show": true,
        "total": false,
        "values": false
      },
      "lines": true,
      "linewidth": 1,
      "nullPointMode": "null",
      "options": {
        "alertThreshold": true
      },
      "percentage": false,
      "pluginVersion": "7.3.7",
      "pointradius": 2,
      "points": false,
      "renderer": "flot",
      "seriesOverrides": [],
      "spaceLength": 10,
      "stack": false,
      "steppedLine": false,
      "targets": [
        {
          "expr": "sum(increase(endpoint_monitoring_count{job=\"monitoring\",endpoint_name=\"$endpoint\"}[30m])) by (http_code,path)",
          "interval": "",
          "legendFormat": "",
          "refId": "A"
        }
      ],
      "thresholds": [],
      "timeFrom": null,
      "timeRegions": [],
      "timeShift": null,
      "title": "Response Codes",
      "tooltip": {
        "shared": true,
        "sort": 0,
        "value_type": "individual"
      },
      "type": "graph",
      "xaxis": {
        "buckets": null,
        "mode": "time",
        "name": null,
        "show": true,
        "values": []
      },
      "yaxes": [
        {
          "$$hashKey": "object:254",
          "format": "short",
          "label": null,
          "logBase": 1,
          "max": null,
          "min": null,
          "show": true
        },
        {
          "$$hashKey": "object:255",
          "format": "short",
          "label": null,
          "logBase": 1,
          "max": null,
          "min": null,
          "show": true
        }
      ],
      "yaxis": {
        "align": false,
        "alignLevel": null
      }
    },
    {
      "datasource": null,
      "description": "Number of HTTP 5XX responses - until now",
      "fieldConfig": {
        "defaults": {
          "custom": {},
          "mappings": [],
          "thresholds": {
            "mode": "absolute",
            "steps": [
              {
                "color": "orange",
                "value": null
              },
              {
                "color": "orange",
                "value": 80
              }
            ]
          }
        },
        "overrides": []
      },
      "gridPos": {
        "h": 5,
        "w": 5,
        "x": 0,
        "y": 15
      },
      "id": 14,
      "options": {
        "colorMode": "value",
        "graphMode": "area",
        "justifyMode": "auto",
        "orientation": "auto",
        "reduceOptions": {
          "calcs": [
            "mean"
          ],
          "fields": "",
          "values": false
        },
        "textMode": "auto"
      },
      "pluginVersion": "7.3.7",
      "targets": [
        {
          "expr": "sum(endpoint_monitoring_count{http_code=~\"5..\",endpoint_name=\"$endpoint\"})",
          "interval": "",
          "legendFormat": "",
          "refId": "A"
        }
      ],
      "timeFrom": null,
      "timeShift": null,
      "title": "HTTP 5XX Total",
      "type": "stat"
    }
  ],
  "refresh": false,
  "schemaVersion": 26,
  "style": "dark",
  "tags": [],
  "templating": {
    "list": [
      {
        "allValue": null,
        "current": {
          "selected": false,
          "text": "",
          "value": ""
        },
        "datasource": "Prometheus",
        "definition": "endpoint_monitoring_bucket",
        "error": null,
        "hide": 0,
        "includeAll": false,
        "label": "Select Endpoint",
        "multi": false,
        "name": "endpoint",
        "options": [],
        "query": "endpoint_monitoring_bucket",
        "refresh": 1,
        "regex": ".*name=\"(.*?)\".*",
        "skipUrlSync": false,
        "sort": 1,
        "tagValuesQuery": "",
        "tags": [],
        "tagsQuery": "",
        "type": "query",
        "useTags": false
      }
    ]
  },
  "time": {
    "from": "now-30m",
    "to": "now"
  },
  "timepicker": {},
  "timezone": "",
  "title": "Monitoring",
  "uid": "0wC6v48Mz",
  "version": 1
}